haproxy_stats-1.5.dist-info/DESCRIPTION.rst
haproxy_stats-1.5.dist-info/METADATA
haproxy_stats-1.5.dist-info/RECORD
haproxy_stats-1.5.dist-info/WHEEL
haproxy_stats-1.5.dist-info/metadata.json
haproxy_stats-1.5.dist-info/top_level.txt
haproxystats/__init__.py
haproxystats/version.py
