Metadata-Version: 2.0
Name: haproxy-stats
Version: 1.5
Summary: Library for collecting and parsing HAProxy server stats
Home-page: https://github.com/bcicen/haproxy-stats
Author: Bradley Cicenas
Author-email: bradley.cicenas@gmail.com
License: http://opensource.org/licenses/MIT
Keywords: haproxy stats monitoring devops
Platform: UNKNOWN
Classifier: License :: OSI Approved :: MIT License 
Classifier: Natural Language :: English
Classifier: Programming Language :: Python
Classifier: Programming Language :: Python :: 2
Classifier: Programming Language :: Python :: 3
Requires-Dist: requests (>=2.6.2)
